RelocateFile-0.0.1.data/data/src/FileMover.py/FileMover.py
src/FileMover.py
src/__init__.py
RelocateFile-0.0.1.dist-info/LICENCE
RelocateFile-0.0.1.dist-info/METADATA
RelocateFile-0.0.1.dist-info/WHEEL
RelocateFile-0.0.1.dist-info/top_level.txt
RelocateFile-0.0.1.dist-info/RECORD
